{
	"name": "winterMob0",
	"plugin-id": "Sprite",
	"sid": 872544445264117,
	"isGlobal": false,
	"instanceVariables": [
		{
			"name": "currentX",
			"type": "number",
			"desc": "",
			"show": true,
			"sid": 635982524261636
		}
	],
	"behaviorTypes": [
		{
			"behaviorId": "Orbit",
			"name": "Orbit",
			"sid": 729494977265852
		}
	],
	"effectTypes": [],
	"animations": {
		"items": [
			{
				"frames": [
					{
						"width": 48,
						"height": 48,
						"originX": 0.5,
						"originY": 0.5,
						"originalSource": "",
						"exportFormat": "lossless",
						"exportQuality": 0.8,
						"imageSpriteId": 4526702,
						"collisionPoly": {
							"points": [
								0.1875,
								1,
								0.1875,
								0.9791666666666666,
								0.875,
								0.9791666666666666,
								0.875,
								1
							]
						},
						"useCollisionPoly": true,
						"duration": 1
					},
					{
						"width": 48,
						"height": 48,
						"originX": 0.5,
						"originY": 0.5,
						"originalSource": "",
						"exportFormat": "lossless",
						"exportQuality": 0.8,
						"imageSpriteId": 3437434,
						"collisionPoly": {
							"points": [
								0.1875,
								1,
								0.1875,
								0.9791666666666666,
								0.875,
								0.9791666666666666,
								0.875,
								1
							]
						},
						"useCollisionPoly": true,
						"duration": 1
					},
					{
						"width": 48,
						"height": 48,
						"originX": 0.5,
						"originY": 0.5,
						"originalSource": "",
						"exportFormat": "lossless",
						"exportQuality": 0.8,
						"imageSpriteId": 9689243,
						"collisionPoly": {
							"points": [
								0.1875,
								1,
								0.1875,
								0.9791666666666666,
								0.875,
								0.9791666666666666,
								0.875,
								1
							]
						},
						"useCollisionPoly": true,
						"duration": 1
					},
					{
						"width": 48,
						"height": 48,
						"originX": 0.5,
						"originY": 0.5,
						"originalSource": "",
						"exportFormat": "lossless",
						"exportQuality": 0.8,
						"imageSpriteId": 4824062,
						"collisionPoly": {
							"points": [
								0.1875,
								1,
								0.1875,
								0.9791666666666666,
								0.875,
								0.9791666666666666,
								0.875,
								1
							]
						},
						"useCollisionPoly": true,
						"duration": 1
					},
					{
						"width": 48,
						"height": 48,
						"originX": 0.5,
						"originY": 0.5,
						"originalSource": "",
						"exportFormat": "lossless",
						"exportQuality": 0.8,
						"imageSpriteId": 3517328,
						"collisionPoly": {
							"points": [
								0.1875,
								1,
								0.1875,
								0.9791666666666666,
								0.875,
								0.9791666666666666,
								0.875,
								1
							]
						},
						"useCollisionPoly": true,
						"duration": 1
					},
					{
						"width": 48,
						"height": 48,
						"originX": 0.5,
						"originY": 0.5,
						"originalSource": "",
						"exportFormat": "lossless",
						"exportQuality": 0.8,
						"imageSpriteId": 2632446,
						"collisionPoly": {
							"points": [
								0.1875,
								1,
								0.1875,
								0.9791666666666666,
								0.875,
								0.9791666666666666,
								0.875,
								1
							]
						},
						"useCollisionPoly": true,
						"duration": 1
					},
					{
						"width": 48,
						"height": 48,
						"originX": 0.5,
						"originY": 0.5,
						"originalSource": "",
						"exportFormat": "lossless",
						"exportQuality": 0.8,
						"imageSpriteId": 3515141,
						"collisionPoly": {
							"points": [
								0.1875,
								1,
								0.1875,
								0.9791666666666666,
								0.875,
								0.9791666666666666,
								0.875,
								1
							]
						},
						"useCollisionPoly": true,
						"duration": 1
					},
					{
						"width": 48,
						"height": 48,
						"originX": 0.5,
						"originY": 0.5,
						"originalSource": "",
						"exportFormat": "lossless",
						"exportQuality": 0.8,
						"imageSpriteId": 1302894,
						"collisionPoly": {
							"points": [
								0.1875,
								1,
								0.1875,
								0.9791666666666666,
								0.875,
								0.9791666666666666,
								0.875,
								1
							]
						},
						"useCollisionPoly": true,
						"duration": 1
					},
					{
						"width": 48,
						"height": 48,
						"originX": 0.5,
						"originY": 0.5,
						"originalSource": "",
						"exportFormat": "lossless",
						"exportQuality": 0.8,
						"imageSpriteId": 615687,
						"collisionPoly": {
							"points": [
								0.17708333333333334,
								0.9895833333333334,
								0.17708333333333334,
								0.9687500000000001,
								0.8854166666666666,
								0.9687500000000001,
								0.8854166666666666,
								0.9895833333333334
							]
						},
						"useCollisionPoly": true,
						"duration": 1
					},
					{
						"width": 48,
						"height": 48,
						"originX": 0.5,
						"originY": 0.5,
						"originalSource": "",
						"exportFormat": "lossless",
						"exportQuality": 0.8,
						"imageSpriteId": 5027629,
						"collisionPoly": {
							"points": [
								0.1875,
								1,
								0.1875,
								0.9791666666666666,
								0.875,
								0.9791666666666666,
								0.875,
								1
							]
						},
						"useCollisionPoly": true,
						"duration": 1
					},
					{
						"width": 48,
						"height": 48,
						"originX": 0.5,
						"originY": 0.5,
						"originalSource": "",
						"exportFormat": "lossless",
						"exportQuality": 0.8,
						"imageSpriteId": 4576504,
						"collisionPoly": {
							"points": [
								0.1875,
								1,
								0.1875,
								0.9791666666666666,
								0.875,
								0.9791666666666666,
								0.875,
								1
							]
						},
						"useCollisionPoly": true,
						"duration": 1
					},
					{
						"width": 48,
						"height": 48,
						"originX": 0.5,
						"originY": 0.5,
						"originalSource": "",
						"exportFormat": "lossless",
						"exportQuality": 0.8,
						"imageSpriteId": 4917234,
						"collisionPoly": {
							"points": [
								0.1875,
								1,
								0.1875,
								0.9791666666666666,
								0.875,
								0.9791666666666666,
								0.875,
								1
							]
						},
						"useCollisionPoly": true,
						"duration": 1
					},
					{
						"width": 48,
						"height": 48,
						"originX": 0.5,
						"originY": 0.5,
						"originalSource": "",
						"exportFormat": "lossless",
						"exportQuality": 0.8,
						"imageSpriteId": 7022272,
						"collisionPoly": {
							"points": [
								0.1875,
								1,
								0.1875,
								0.9791666666666666,
								0.875,
								0.9791666666666666,
								0.875,
								1
							]
						},
						"useCollisionPoly": true,
						"duration": 1
					},
					{
						"width": 48,
						"height": 48,
						"originX": 0.5,
						"originY": 0.5,
						"originalSource": "",
						"exportFormat": "lossless",
						"exportQuality": 0.8,
						"imageSpriteId": 2327465,
						"collisionPoly": {
							"points": [
								0.1875,
								1,
								0.1875,
								0.9791666666666666,
								0.875,
								0.9791666666666666,
								0.875,
								1
							]
						},
						"useCollisionPoly": true,
						"duration": 1
					},
					{
						"width": 48,
						"height": 48,
						"originX": 0.5,
						"originY": 0.5,
						"originalSource": "",
						"exportFormat": "lossless",
						"exportQuality": 0.8,
						"imageSpriteId": 8389068,
						"collisionPoly": {
							"points": [
								0.1875,
								1,
								0.1875,
								0.9791666666666666,
								0.875,
								0.9791666666666666,
								0.875,
								1
							]
						},
						"useCollisionPoly": true,
						"duration": 1
					},
					{
						"width": 48,
						"height": 48,
						"originX": 0.5,
						"originY": 0.5,
						"originalSource": "",
						"exportFormat": "lossless",
						"exportQuality": 0.8,
						"imageSpriteId": 6519455,
						"collisionPoly": {
							"points": [
								0.1875,
								1,
								0.1875,
								0.9791666666666666,
								0.875,
								0.9791666666666666,
								0.875,
								1
							]
						},
						"useCollisionPoly": true,
						"duration": 1
					}
				],
				"sid": 998580655757237,
				"name": "Animation 1",
				"isLooping": true,
				"isPingPong": false,
				"repeatCount": 1,
				"repeatTo": 0,
				"speed": 5
			}
		],
		"subfolders": []
	}
}