{
	"name": "arrowSymbol",
	"plugin-id": "Sprite",
	"sid": 948973992394330,
	"isGlobal": false,
	"instanceVariables": [],
	"behaviorTypes": [
		{
			"behaviorId": "Orbit",
			"name": "Orbit",
			"sid": 393147698298576
		}
	],
	"effectTypes": [],
	"animations": {
		"items": [
			{
				"frames": [
					{
						"width": 66,
						"height": 18,
						"originX": 0.5,
						"originY": 0.05555555555555555,
						"originalSource": "",
						"exportFormat": "lossless",
						"exportQuality": 0.8,
						"imageSpriteId": 3721177,
						"collisionPoly": {
							"points": [
								0.3787878787878788,
								0.1111111111111111,
								0.6212121212121212,
								0.1111111111111111,
								0.6212121212121212,
								0.8888888888888888,
								0.3787878787878788,
								0.8888888888888888
							]
						},
						"useCollisionPoly": true,
						"duration": 1
					},
					{
						"width": 66,
						"height": 18,
						"originX": 0.5,
						"originY": 0.05555555555555555,
						"originalSource": "",
						"exportFormat": "lossless",
						"exportQuality": 0.8,
						"imageSpriteId": 6200557,
						"collisionPoly": {
							"points": [
								0.3787878787878788,
								0.1111111111111111,
								0.6212121212121212,
								0.1111111111111111,
								0.6212121212121212,
								0.8888888888888888,
								0.3787878787878788,
								0.8888888888888888
							]
						},
						"useCollisionPoly": true,
						"duration": 1
					},
					{
						"width": 66,
						"height": 18,
						"originX": 0.5,
						"originY": 0.05555555555555555,
						"originalSource": "",
						"exportFormat": "lossless",
						"exportQuality": 0.8,
						"imageSpriteId": 2398650,
						"collisionPoly": {
							"points": [
								0.3787878787878788,
								0.1111111111111111,
								0.6212121212121212,
								0.1111111111111111,
								0.6212121212121212,
								0.8888888888888888,
								0.3787878787878788,
								0.8888888888888888
							]
						},
						"useCollisionPoly": true,
						"duration": 1
					},
					{
						"width": 66,
						"height": 18,
						"originX": 0.5,
						"originY": 0.05555555555555555,
						"originalSource": "",
						"exportFormat": "lossless",
						"exportQuality": 0.8,
						"imageSpriteId": 829806,
						"collisionPoly": {
							"points": [
								0.3787878787878788,
								0.1111111111111111,
								0.6212121212121212,
								0.1111111111111111,
								0.6212121212121212,
								0.8888888888888888,
								0.3787878787878788,
								0.8888888888888888
							]
						},
						"useCollisionPoly": true,
						"duration": 1
					},
					{
						"width": 66,
						"height": 18,
						"originX": 0.5,
						"originY": 0.05555555555555555,
						"originalSource": "",
						"exportFormat": "lossless",
						"exportQuality": 0.8,
						"imageSpriteId": 5479037,
						"collisionPoly": {
							"points": [
								0.3787878787878788,
								0.1111111111111111,
								0.6212121212121212,
								0.1111111111111111,
								0.6212121212121212,
								0.8888888888888888,
								0.3787878787878788,
								0.8888888888888888
							]
						},
						"useCollisionPoly": true,
						"duration": 1
					},
					{
						"width": 66,
						"height": 18,
						"originX": 0.5,
						"originY": 0.05555555555555555,
						"originalSource": "",
						"exportFormat": "lossless",
						"exportQuality": 0.8,
						"imageSpriteId": 1797685,
						"collisionPoly": {
							"points": [
								0.3787878787878788,
								0.1111111111111111,
								0.6212121212121212,
								0.1111111111111111,
								0.6212121212121212,
								0.8888888888888888,
								0.3787878787878788,
								0.8888888888888888
							]
						},
						"useCollisionPoly": true,
						"duration": 1
					},
					{
						"width": 66,
						"height": 18,
						"originX": 0.5,
						"originY": 0.05555555555555555,
						"originalSource": "",
						"exportFormat": "lossless",
						"exportQuality": 0.8,
						"imageSpriteId": 9853848,
						"collisionPoly": {
							"points": [
								0.3787878787878788,
								0.1111111111111111,
								0.6212121212121212,
								0.1111111111111111,
								0.6212121212121212,
								0.8888888888888888,
								0.3787878787878788,
								0.8888888888888888
							]
						},
						"useCollisionPoly": true,
						"duration": 1
					},
					{
						"width": 66,
						"height": 18,
						"originX": 0.5,
						"originY": 0.05555555555555555,
						"originalSource": "",
						"exportFormat": "lossless",
						"exportQuality": 0.8,
						"imageSpriteId": 7000784,
						"collisionPoly": {
							"points": [
								0.3787878787878788,
								0.1111111111111111,
								0.6212121212121212,
								0.1111111111111111,
								0.6212121212121212,
								0.8888888888888888,
								0.3787878787878788,
								0.8888888888888888
							]
						},
						"useCollisionPoly": true,
						"duration": 1
					},
					{
						"width": 66,
						"height": 18,
						"originX": 0.5,
						"originY": 0.05555555555555555,
						"originalSource": "",
						"exportFormat": "lossless",
						"exportQuality": 0.8,
						"imageSpriteId": 8243285,
						"collisionPoly": {
							"points": [
								0.3787878787878788,
								0.1111111111111111,
								0.6212121212121212,
								0.1111111111111111,
								0.6212121212121212,
								0.8888888888888888,
								0.3787878787878788,
								0.8888888888888888
							]
						},
						"useCollisionPoly": true,
						"duration": 1
					},
					{
						"width": 66,
						"height": 18,
						"originX": 0.5,
						"originY": 0.05555555555555555,
						"originalSource": "",
						"exportFormat": "lossless",
						"exportQuality": 0.8,
						"imageSpriteId": 76140,
						"collisionPoly": {
							"points": [
								0.3787878787878788,
								0.1111111111111111,
								0.6212121212121212,
								0.1111111111111111,
								0.6212121212121212,
								0.8888888888888888,
								0.3787878787878788,
								0.8888888888888888
							]
						},
						"useCollisionPoly": true,
						"duration": 1
					},
					{
						"width": 66,
						"height": 18,
						"originX": 0.5,
						"originY": 0.05555555555555555,
						"originalSource": "",
						"exportFormat": "lossless",
						"exportQuality": 0.8,
						"imageSpriteId": 2840163,
						"collisionPoly": {
							"points": [
								0.3787878787878788,
								0.1111111111111111,
								0.6212121212121212,
								0.1111111111111111,
								0.6212121212121212,
								0.8888888888888888,
								0.3787878787878788,
								0.8888888888888888
							]
						},
						"useCollisionPoly": true,
						"duration": 1
					},
					{
						"width": 66,
						"height": 18,
						"originX": 0.5,
						"originY": 0.05555555555555555,
						"originalSource": "",
						"exportFormat": "lossless",
						"exportQuality": 0.8,
						"imageSpriteId": 3027001,
						"collisionPoly": {
							"points": [
								0.3787878787878788,
								0.1111111111111111,
								0.6212121212121212,
								0.1111111111111111,
								0.6212121212121212,
								0.8888888888888888,
								0.3787878787878788,
								0.8888888888888888
							]
						},
						"useCollisionPoly": true,
						"duration": 1
					},
					{
						"width": 66,
						"height": 18,
						"originX": 0.5,
						"originY": 0.05555555555555555,
						"originalSource": "",
						"exportFormat": "lossless",
						"exportQuality": 0.8,
						"imageSpriteId": 169827,
						"collisionPoly": {
							"points": [
								0.3787878787878788,
								0.1111111111111111,
								0.6212121212121212,
								0.1111111111111111,
								0.6212121212121212,
								0.8888888888888888,
								0.3787878787878788,
								0.8888888888888888
							]
						},
						"useCollisionPoly": true,
						"duration": 1
					},
					{
						"width": 66,
						"height": 18,
						"originX": 0.5,
						"originY": 0.05555555555555555,
						"originalSource": "",
						"exportFormat": "lossless",
						"exportQuality": 0.8,
						"imageSpriteId": 6961369,
						"collisionPoly": {
							"points": [
								0.3787878787878788,
								0.1111111111111111,
								0.6212121212121212,
								0.1111111111111111,
								0.6212121212121212,
								0.8888888888888888,
								0.3787878787878788,
								0.8888888888888888
							]
						},
						"useCollisionPoly": true,
						"duration": 1
					},
					{
						"width": 66,
						"height": 18,
						"originX": 0.5,
						"originY": 0.05555555555555555,
						"originalSource": "",
						"exportFormat": "lossless",
						"exportQuality": 0.8,
						"imageSpriteId": 2112761,
						"collisionPoly": {
							"points": [
								0.3787878787878788,
								0.1111111111111111,
								0.6212121212121212,
								0.1111111111111111,
								0.6212121212121212,
								0.8888888888888888,
								0.3787878787878788,
								0.8888888888888888
							]
						},
						"useCollisionPoly": true,
						"duration": 1
					},
					{
						"width": 66,
						"height": 18,
						"originX": 0.5,
						"originY": 0.05555555555555555,
						"originalSource": "",
						"exportFormat": "lossless",
						"exportQuality": 0.8,
						"imageSpriteId": 8003924,
						"collisionPoly": {
							"points": [
								0.3787878787878788,
								0.1111111111111111,
								0.6212121212121212,
								0.1111111111111111,
								0.6212121212121212,
								0.8888888888888888,
								0.3787878787878788,
								0.8888888888888888
							]
						},
						"useCollisionPoly": true,
						"duration": 1
					},
					{
						"width": 66,
						"height": 18,
						"originX": 0.5,
						"originY": 0.05555555555555555,
						"originalSource": "",
						"exportFormat": "lossless",
						"exportQuality": 0.8,
						"imageSpriteId": 3154115,
						"collisionPoly": {
							"points": [
								0.3787878787878788,
								0.1111111111111111,
								0.6212121212121212,
								0.1111111111111111,
								0.6212121212121212,
								0.8888888888888888,
								0.3787878787878788,
								0.8888888888888888
							]
						},
						"useCollisionPoly": true,
						"duration": 8
					}
				],
				"sid": 271439051837091,
				"name": "Animation 1",
				"isLooping": true,
				"isPingPong": false,
				"repeatCount": 1,
				"repeatTo": 0,
				"speed": 10
			},
			{
				"frames": [
					{
						"width": 22,
						"height": 18,
						"originX": 0.5454545454545454,
						"originY": 0.5,
						"originalSource": "",
						"exportFormat": "lossless",
						"exportQuality": 0.8,
						"imageSpriteId": 7899144,
						"collisionPoly": {
							"points": [
								0.06818181818181818,
								0,
								1,
								0,
								1,
								1,
								0.06818181818181818,
								1
							]
						},
						"useCollisionPoly": true,
						"duration": 1
					}
				],
				"sid": 563798035836597,
				"name": "Animation 2",
				"isLooping": false,
				"isPingPong": false,
				"repeatCount": 1,
				"repeatTo": 0,
				"speed": 5
			}
		],
		"subfolders": []
	}
}